udbserver/__init__.py
udbserver/libudbserver.so
udbserver-0.2.1.dist-info/METADATA
udbserver-0.2.1.dist-info/WHEEL
udbserver-0.2.1.dist-info/top_level.txt
udbserver-0.2.1.dist-info/RECORD
