Metadata-Version: 2.4
Name: udbserver
Version: 0.2.1
Summary: Python bindings of udbserver
Author-email: Bet4 <0xbet4@gmail.com>
License-Expression: MIT
Project-URL: homepage, https://github.com/bet4it/udbserver
Classifier: Intended Audience :: Developers
Classifier: Programming Language :: Python :: 3
Classifier: Operating System :: POSIX
Classifier: Operating System :: MacOS :: MacOS X
Classifier: Operating System :: Microsoft :: Windows
Classifier: Topic :: Software Development :: Debuggers
Requires-Dist: unicorn>=2
